.travis.yml
CHANGES.rst
CONTRIBUTORS.rst
MANIFEST.in
Makefile
README.rst
bootstrap.py
buildout.cfg
setup.py
travis.cfg
docs/LICENSE.GPL
docs/LICENSE.rst
src/collective/__init__.py
src/collective.geo.leaflet.egg-info/PKG-INFO
src/collective.geo.leaflet.egg-info/SOURCES.txt
src/collective.geo.leaflet.egg-info/dependency_links.txt
src/collective.geo.leaflet.egg-info/entry_points.txt
src/collective.geo.leaflet.egg-info/namespace_packages.txt
src/collective.geo.leaflet.egg-info/not-zip-safe
src/collective.geo.leaflet.egg-info/requires.txt
src/collective.geo.leaflet.egg-info/top_level.txt
src/collective/geo/__init__.py
src/collective/geo/leaflet/__init__.py
src/collective/geo/leaflet/configure.zcml
src/collective/geo/leaflet/geomap.py
src/collective/geo/leaflet/indexer.py
src/collective/geo/leaflet/interfaces.py
src/collective/geo/leaflet/maplayers.py
src/collective/geo/leaflet/profile.py
src/collective/geo/leaflet/profiles.zcml
src/collective/geo/leaflet/setuphandlers.py
src/collective/geo/leaflet/testing.py
src/collective/geo/leaflet/testing.zcml
src/collective/geo/leaflet/upgradehandlers.py
src/collective/geo/leaflet/utils.py
src/collective/geo/leaflet/browser/__init__.py
src/collective/geo/leaflet/browser/collectivegeoleaflet_macros.py
src/collective/geo/leaflet/browser/configure.zcml
src/collective/geo/leaflet/browser/viewlets.py
src/collective/geo/leaflet/browser/views.py
src/collective/geo/leaflet/browser/layers/google_hyb.pt
src/collective/geo/leaflet/browser/layers/google_map.pt
src/collective/geo/leaflet/browser/layers/google_sat.pt
src/collective/geo/leaflet/browser/layers/google_ter.pt
src/collective/geo/leaflet/browser/layers/osm.pt
src/collective/geo/leaflet/browser/static/cgeoleaflet.css
src/collective/geo/leaflet/browser/static/cgeoleaflet.js
src/collective/geo/leaflet/browser/static/cgeoleaflet_layers.js
src/collective/geo/leaflet/browser/static/leaflet-google.js
src/collective/geo/leaflet/browser/templates/collectivegeoleaflet_macros.pt
src/collective/geo/leaflet/browser/templates/geo-leaflet.pt
src/collective/geo/leaflet/browser/templates/leafletcontentviewlet.pt
src/collective/geo/leaflet/locales/collective.geo.leaflet.pot
src/collective/geo/leaflet/locales/update.sh
src/collective/geo/leaflet/locales/en/LC_MESSAGES/collective.geo.leaflet.po
src/collective/geo/leaflet/locales/fr/LC_MESSAGES/collective.geo.leaflet.po
