Metadata-Version: 1.1
Name: collective.geo.leaflet
Version: 0.2.5
Summary: Add geo views for dexterity content with leaflet js library
Home-page: http://pypi.python.org/pypi/collective.geo.leaflet
Author: Benoît Suttor
Author-email: benoit.suttor@imio.be
License: GPL
Keywords: leaflet collective.geo geo plone dexterity map
Platform: UNKNOWN
Classifier: Environment :: Web Environment
Classifier: Framework :: Plone
Classifier: Framework :: Plone :: 4.3
Classifier: Programming Language :: Python
Classifier: Programming Language :: Python :: 2.7
